Fabric39-1.15.3.post1.dist-info/RECORD
Fabric39-1.15.3.post1.dist-info/metadata.json
Fabric39-1.15.3.post1.dist-info/WHEEL
Fabric39-1.15.3.post1.dist-info/entry_points.txt
Fabric39-1.15.3.post1.dist-info/DESCRIPTION.rst
Fabric39-1.15.3.post1.dist-info/top_level.txt
Fabric39-1.15.3.post1.dist-info/METADATA
fabric/auth.py
fabric/tasks.py
fabric/version.py
fabric/io.py
fabric/__init__.py
fabric/docs.py
fabric/api.py
fabric/operations.py
fabric/context_managers.py
fabric/utils.py
fabric/network.py
fabric/exceptions.py
fabric/task_utils.py
fabric/sftp.py
fabric/job_queue.py
fabric/main.py
fabric/thread_handling.py
fabric/__main__.py
fabric/state.py
fabric/colors.py
fabric/decorators.py
fabric/contrib/django.py
fabric/contrib/console.py
fabric/contrib/files.py
fabric/contrib/__init__.py
fabric/contrib/project.py
