Metadata-Version: 2.0
Name: Fabric39
Version: 1.15.3.post1
Summary: Fabric is a simple, Pythonic tool for remote execution and deployment (py2.7/py3.4+ compatible fork).
Home-page: https://github.com/Parsely/fabric/
Author: Jeff Forcier
Author-email: jeff@bitprophet.org
Maintainer: Brian Abelson
Maintainer-email: brian.abelson@parsely.com
License: UNKNOWN
Platform: UNKNOWN
Classifier: Development Status :: 5 - Production/Stable
Classifier: Environment :: Console
Classifier: Intended Audience :: Developers
Classifier: Intended Audience :: System Administrators
Classifier: License :: OSI Approved :: BSD License
Classifier: Operating System :: MacOS :: MacOS X
Classifier: Operating System :: Unix
Classifier: Operating System :: POSIX
Classifier: Programming Language :: Python
Classifier: Programming Language :: Python :: 2
Classifier: Programming Language :: Python :: 2.7
Classifier: Programming Language :: Python :: 3
Classifier: Programming Language :: Python :: 3.4
Classifier: Programming Language :: Python :: 3.5
Classifier: Programming Language :: Python :: 3.9
Classifier: Topic :: Software Development
Classifier: Topic :: Software Development :: Build Tools
Classifier: Topic :: Software Development :: Libraries
Classifier: Topic :: Software Development :: Libraries :: Python Modules
Classifier: Topic :: System :: Clustering
Classifier: Topic :: System :: Software Distribution
Classifier: Topic :: System :: Systems Administration
License-File: LICENSE
License-File: AUTHORS
Requires-Dist: paramiko (>=2.0,<3.0)
Requires-Dist: six (>=1.10.0)
Requires-Dist: pathos (==0.2.8)
